{"courses":[{"subject":"TAM","number":195,"name":"Mechanics in the Modern World","counts":[22,0,0,0],"allTerms":["Fall 2025","Fall 2024","Fall 2023","Fall 2022","Fall 2021","Fall 2020","Fall 2019","Fall 2018","Fall 2017","Fall 2016","Fall 2015","Fall 2014","Fall 2013","Fall 2012","Fall 2011","Fall 2010","Fall 2009","Fall 2008","Fall 2007","Fall 2006","Fall 2005","Fall 2004"]},{"subject":"TAM","number":199,"name":"Undergraduate Open Seminar","counts":[22,20,21,0],"allTerms":["Fall 2025","Summer 2025","Spring 2025","Fall 2024","Summer 2024","Spring 2024","Fall 2023","Summer 2023","Spring 2023","Fall 2022","Summer 2022","Spring 2022","Fall 2021","Summer 2021","Fall 2020","Summer 2020","Spring 2020","Fall 2019","Summer 2019","Spring 2019","Fall 2018","Summer 2018","Spring 2018","Fall 2017","Summer 2017","Spring 2017","Fall 2016","Summer 2016","Spring 2016","Fall 2015","Summer 2015","Spring 2015","Fall 2014","Summer 2014","Spring 2014","Fall 2013","Summer 2013","Spring 2013","Fall 2012","Summer 2012","Spring 2012","Fall 2011","Summer 2011","Spring 2011","Fall 2010","Summer 2010","Spring 2010","Fall 2009","Summer 2009","Spring 2009","Fall 2008","Summer 2008","Spring 2008","Fall 2007","Summer 2007","Spring 2007","Fall 2006","Summer 2006","Spring 2006","Fall 2005","Summer 2005","Spring 2005","Fall 2004"]},{"subject":"TAM","number":201,"name":"Mechanics for Technol & Mgmt","counts":[14,7,0,0],"allTerms":["Fall 2025","Fall 2024","Fall 2023","Fall 2022","Fall 2021","Fall 2020","Fall 2019","Fall 2018","Fall 2017","Fall 2016","Fall 2015","Fall 2014","Fall 2013","Fall 2012","Spring 2011","Spring 2010","Spring 2009","Spring 2008","Spring 2007","Spring 2006","Spring 2005"]},{"subject":"TAM","number":210,"name":"Introduction to Statics","counts":[22,21,1,0],"allTerms":["Fall 2025","Summer 2025","Spring 2025","Fall 2024","Spring 2024","Fall 2023","Spring 2023","Fall 2022","Spring 2022","Fall 2021","Spring 2021","Fall 2020","Spring 2020","Fall 2019","Spring 2019","Fall 2018","Spring 2018","Fall 2017","Spring 2017","Fall 2016","Spring 2016","Fall 2015","Spring 2015","Fall 2014","Spring 2014","Fall 2013","Spring 2013","Fall 2012","Spring 2012","Fall 2011","Spring 2011","Fall 2010","Spring 2010","Fall 2009","Spring 2009","Fall 2008","Spring 2008","Fall 2007","Spring 2007","Fall 2006","Spring 2006","Fall 2005","Spring 2005","Fall 2004"]},{"subject":"TAM","number":211,"name":"Statics","counts":[22,21,1,0],"allTerms":["Fall 2025","Summer 2025","Spring 2025","Fall 2024","Spring 2024","Fall 2023","Spring 2023","Fall 2022","Spring 2022","Fall 2021","Spring 2021","Fall 2020","Spring 2020","Fall 2019","Spring 2019","Fall 2018","Spring 2018","Fall 2017","Spring 2017","Fall 2016","Spring 2016","Fall 2015","Spring 2015","Fall 2014","Spring 2014","Fall 2013","Spring 2013","Fall 2012","Spring 2012","Fall 2011","Spring 2011","Fall 2010","Spring 2010","Fall 2009","Spring 2009","Fall 2008","Spring 2008","Fall 2007","Spring 2007","Fall 2006","Spring 2006","Fall 2005","Spring 2005","Fall 2004"]},{"subject":"TAM","number":212,"name":"Introductory Dynamics","counts":[22,21,21,0],"allTerms":["Fall 2025","Summer 2025","Spring 2025","Fall 2024","Summer 2024","Spring 2024","Fall 2023","Summer 2023","Spring 2023","Fall 2022","Summer 2022","Spring 2022","Fall 2021","Summer 2021","Spring 2021","Fall 2020","Summer 2020","Spring 2020","Fall 2019","Summer 2019","Spring 2019","Fall 2018","Summer 2018","Spring 2018","Fall 2017","Summer 2017","Spring 2017","Fall 2016","Summer 2016","Spring 2016","Fall 2015","Summer 2015","Spring 2015","Fall 2014","Summer 2014","Spring 2014","Fall 2013","Summer 2013","Spring 2013","Fall 2012","Summer 2012","Spring 2012","Fall 2011","Summer 2011","Spring 2011","Fall 2010","Summer 2010","Spring 2010","Fall 2009","Summer 2009","Spring 2009","Fall 2008","Summer 2008","Spring 2008","Fall 2007","Summer 2007","Spring 2007","Fall 2006","Summer 2006","Spring 2006","Fall 2005","Summer 2005","Spring 2005","Fall 2004"]},{"subject":"TAM","number":251,"name":"Introductory Solid Mechanics","counts":[22,21,21,0],"allTerms":["Fall 2025","Summer 2025","Spring 2025","Fall 2024","Summer 2024","Spring 2024","Fall 2023","Summer 2023","Spring 2023","Fall 2022","Summer 2022","Spring 2022","Fall 2021","Summer 2021","Spring 2021","Fall 2020","Summer 2020","Spring 2020","Fall 2019","Summer 2019","Spring 2019","Fall 2018","Summer 2018","Spring 2018","Fall 2017","Summer 2017","Spring 2017","Fall 2016","Summer 2016","Spring 2016","Fall 2015","Summer 2015","Spring 2015","Fall 2014","Summer 2014","Spring 2014","Fall 2013","Summer 2013","Spring 2013","Fall 2012","Summer 2012","Spring 2012","Fall 2011","Summer 2011","Spring 2011","Fall 2010","Summer 2010","Spring 2010","Fall 2009","Summer 2009","Spring 2009","Fall 2008","Summer 2008","Spring 2008","Fall 2007","Summer 2007","Spring 2007","Fall 2006","Summer 2006","Spring 2006","Fall 2005","Summer 2005","Spring 2005","Fall 2004"]},{"subject":"TAM","number":252,"name":"Solid Mechanics Design","counts":[0,21,0,0],"allTerms":["Spring 2025","Spring 2024","Spring 2023","Spring 2022","Spring 2021","Spring 2020","Spring 2019","Spring 2018","Spring 2017","Spring 2016","Spring 2015","Spring 2014","Spring 2013","Spring 2012","Spring 2011","Spring 2010","Spring 2009","Spring 2008","Spring 2007","Spring 2006","Spring 2005"]},{"subject":"TAM","number":270,"name":"Design for Manufacturability","counts":[8,7,0,0],"allTerms":["Fall 2025","Spring 2025","Fall 2024","Spring 2024","Fall 2023","Spring 2023","Fall 2022","Spring 2022","Fall 2021","Spring 2021","Fall 2020","Spring 2020","Fall 2019","Spring 2019","Fall 2018"]},{"subject":"TAM","number":297,"name":"Introductory Independent Study","counts":[9,8,0,0],"allTerms":["Fall 2025","Spring 2025","Fall 2024","Spring 2024","Fall 2023","Spring 2023","Fall 2022","Spring 2022","Fall 2021","Spring 2021","Fall 2020","Spring 2020","Fall 2019","Spring 2019","Fall 2018","Spring 2018","Fall 2017"]},{"subject":"TAM","number":324,"name":"Behavior of Materials","counts":[22,21,0,0],"allTerms":["Fall 2025","Spring 2025","Fall 2024","Spring 2024","Fall 2023","Spring 2023","Fall 2022","Spring 2022","Fall 2021","Spring 2021","Fall 2020","Spring 2020","Fall 2019","Spring 2019","Fall 2018","Spring 2018","Fall 2017","Spring 2017","Fall 2016","Spring 2016","Fall 2015","Spring 2015","Fall 2014","Spring 2014","Fall 2013","Spring 2013","Fall 2012","Spring 2012","Fall 2011","Spring 2011","Fall 2010","Spring 2010","Fall 2009","Spring 2009","Fall 2008","Spring 2008","Fall 2007","Spring 2007","Fall 2006","Spring 2006","Fall 2005","Spring 2005","Fall 2004"]},{"subject":"TAM","number":335,"name":"Introductory Fluid Mechanics","counts":[22,21,21,0],"allTerms":["Fall 2025","Summer 2025","Spring 2025","Fall 2024","Summer 2024","Spring 2024","Fall 2023","Summer 2023","Spring 2023","Fall 2022","Summer 2022","Spring 2022","Fall 2021","Summer 2021","Spring 2021","Fall 2020","Summer 2020","Spring 2020","Fall 2019","Summer 2019","Spring 2019","Fall 2018","Summer 2018","Spring 2018","Fall 2017","Summer 2017","Spring 2017","Fall 2016","Summer 2016","Spring 2016","Fall 2015","Summer 2015","Spring 2015","Fall 2014","Summer 2014","Spring 2014","Fall 2013","Summer 2013","Spring 2013","Fall 2012","Summer 2012","Spring 2012","Fall 2011","Summer 2011","Spring 2011","Fall 2010","Summer 2010","Spring 2010","Fall 2009","Summer 2009","Spring 2009","Fall 2008","Summer 2008","Spring 2008","Fall 2007","Summer 2007","Spring 2007","Fall 2006","Summer 2006","Spring 2006","Fall 2005","Summer 2005","Spring 2005","Fall 2004"]},{"subject":"TAM","number":412,"name":"Intermediate Dynamics","counts":[0,21,0,0],"allTerms":["Spring 2025","Spring 2024","Spring 2023","Spring 2022","Spring 2021","Spring 2020","Spring 2019","Spring 2018","Spring 2017","Spring 2016","Spring 2015","Spring 2014","Spring 2013","Spring 2012","Spring 2011","Spring 2010","Spring 2009","Spring 2008","Spring 2007","Spring 2006","Spring 2005"]},{"subject":"TAM","number":413,"name":"Fund of Engrg Acoustics","counts":[21,12,0,0],"allTerms":["Fall 2025","Fall 2024","Fall 2023","Fall 2022","Fall 2021","Fall 2020","Fall 2019","Fall 2018","Fall 2017","Fall 2016","Spring 2016","Spring 2015","Fall 2014","Spring 2014","Fall 2013","Spring 2013","Fall 2012","Spring 2012","Fall 2011","Spring 2011","Fall 2010","Spring 2010","Fall 2009","Spring 2009","Fall 2008","Spring 2008","Fall 2007","Spring 2007","Fall 2006","Spring 2006","Fall 2005","Spring 2005","Fall 2004"]},{"subject":"TAM","number":416,"name":"Introduction to Nonlinear Dynamics and Vibrations","counts":[5,2,0,0],"allTerms":["Fall 2024","Fall 2022","Fall 2020","Fall 2018","Spring 2017","Fall 2015","Spring 2014"]},{"subject":"TAM","number":424,"name":"Mechanics of Structural Metals","counts":[19,2,0,0],"allTerms":["Fall 2025","Fall 2024","Fall 2023","Fall 2022","Fall 2021","Fall 2020","Fall 2019","Fall 2018","Fall 2017","Fall 2016","Fall 2015","Fall 2014","Fall 2013","Fall 2012","Fall 2011","Fall 2010","Fall 2009","Fall 2008","Fall 2007","Spring 2006","Spring 2005"]},{"subject":"TAM","number":428,"name":"Mechanics of Composites","counts":[17,2,0,0],"allTerms":["Fall 2025","Spring 2024","Spring 2023","Fall 2020","Fall 2019","Fall 2018","Fall 2017","Fall 2016","Fall 2015","Fall 2014","Fall 2013","Fall 2011","Fall 2010","Fall 2009","Fall 2008","Fall 2007","Fall 2006","Fall 2005","Fall 2004"]},{"subject":"TAM","number":435,"name":"Intermediate Fluid Mechanics","counts":[21,0,0,0],"allTerms":["Fall 2025","Fall 2024","Fall 2023","Fall 2022","Fall 2021","Fall 2020","Fall 2019","Fall 2018","Fall 2017","Fall 2016","Fall 2015","Fall 2014","Fall 2013","Fall 2012","Fall 2011","Fall 2010","Fall 2009","Fall 2008","Fall 2007","Fall 2006","Fall 2004"]},{"subject":"TAM","number":445,"name":"Continuum Mechanics","counts":[0,21,0,0],"allTerms":["Spring 2025","Spring 2024","Spring 2023","Spring 2022","Spring 2021","Spring 2020","Spring 2019","Spring 2018","Spring 2017","Spring 2016","Spring 2015","Spring 2014","Spring 2013","Spring 2012","Spring 2011","Spring 2010","Spring 2009","Spring 2008","Spring 2007","Spring 2006","Spring 2005"]},{"subject":"TAM","number":451,"name":"Intermediate Solid Mechanics","counts":[22,0,0,0],"allTerms":["Fall 2025","Fall 2024","Fall 2023","Fall 2022","Fall 2021","Fall 2020","Fall 2019","Fall 2018","Fall 2017","Fall 2016","Fall 2015","Fall 2014","Fall 2013","Fall 2012","Fall 2011","Fall 2010","Fall 2009","Fall 2008","Fall 2007","Fall 2006","Fall 2005","Fall 2004"]},{"subject":"TAM","number":456,"name":"Experimental Stress Analysis","counts":[0,21,0,0],"allTerms":["Spring 2025","Spring 2024","Spring 2023","Spring 2022","Spring 2021","Spring 2020","Spring 2019","Spring 2018","Spring 2017","Spring 2016","Spring 2015","Spring 2014","Spring 2013","Spring 2012","Spring 2011","Spring 2010","Spring 2009","Spring 2008","Spring 2007","Spring 2006","Spring 2005"]},{"subject":"TAM","number":461,"name":"Cellular Biomechanics","counts":[19,0,0,0],"allTerms":["Fall 2025","Fall 2021","Fall 2020","Fall 2019","Fall 2018","Fall 2017","Fall 2016","Fall 2015","Fall 2014","Fall 2013","Fall 2012","Fall 2011","Fall 2010","Fall 2009","Fall 2008","Fall 2007","Fall 2006","Fall 2005","Fall 2004"]},{"subject":"TAM","number":470,"name":"Computational Mechanics","counts":[22,0,0,0],"allTerms":["Fall 2025","Fall 2024","Fall 2023","Fall 2022","Fall 2021","Fall 2020","Fall 2019","Fall 2018","Fall 2017","Fall 2016","Fall 2015","Fall 2014","Fall 2013","Fall 2012","Fall 2011","Fall 2010","Fall 2009","Fall 2008","Fall 2007","Fall 2006","Fall 2005","Fall 2004"]},{"subject":"TAM","number":497,"name":"Independent Study","counts":[22,21,21,0],"allTerms":["Fall 2025","Summer 2025","Spring 2025","Fall 2024","Summer 2024","Spring 2024","Fall 2023","Summer 2023","Spring 2023","Fall 2022","Summer 2022","Spring 2022","Fall 2021","Summer 2021","Spring 2021","Fall 2020","Summer 2020","Spring 2020","Fall 2019","Summer 2019","Spring 2019","Fall 2018","Summer 2018","Spring 2018","Fall 2017","Summer 2017","Spring 2017","Fall 2016","Summer 2016","Spring 2016","Fall 2015","Summer 2015","Spring 2015","Fall 2014","Summer 2014","Spring 2014","Fall 2013","Summer 2013","Spring 2013","Fall 2012","Summer 2012","Spring 2012","Fall 2011","Summer 2011","Spring 2011","Fall 2010","Summer 2010","Spring 2010","Fall 2009","Summer 2009","Spring 2009","Fall 2008","Summer 2008","Spring 2008","Fall 2007","Summer 2007","Spring 2007","Fall 2006","Summer 2006","Spring 2006","Fall 2005","Summer 2005","Spring 2005","Fall 2004"]},{"subject":"TAM","number":498,"name":"Special Topics","counts":[6,7,0,0],"allTerms":["Spring 2025","Spring 2024","Fall 2021","Spring 2018","Fall 2017","Spring 2017","Fall 2015","Spring 2013","Fall 2012","Spring 2011","Spring 2010","Fall 2006","Fall 2005"]},{"subject":"TAM","number":500,"name":"Seminar","counts":[21,21,0,0],"allTerms":["Fall 2025","Spring 2025","Fall 2024","Spring 2024","Fall 2023","Spring 2023","Fall 2022","Spring 2022","Fall 2021","Spring 2021","Spring 2020","Fall 2019","Spring 2019","Fall 2018","Spring 2018","Fall 2017","Spring 2017","Fall 2016","Spring 2016","Fall 2015","Spring 2015","Fall 2014","Spring 2014","Fall 2013","Spring 2013","Fall 2012","Spring 2012","Fall 2011","Spring 2011","Fall 2010","Spring 2010","Fall 2009","Spring 2009","Fall 2008","Spring 2008","Fall 2007","Spring 2007","Fall 2006","Spring 2006","Fall 2005","Spring 2005","Fall 2004"]},{"subject":"TAM","number":514,"name":"Elastodynamics and Vibrations","counts":[5,3,0,0],"allTerms":["Spring 2025","Spring 2023","Fall 2021","Fall 2019","Fall 2016","Fall 2011","Fall 2009","Spring 2007"]},{"subject":"TAM","number":516,"name":"Dynamical Systems Theory","counts":[0,2,0,0],"allTerms":["Spring 2022","Spring 2019"]},{"subject":"TAM","number":518,"name":"Wave Motion","counts":[6,5,0,0],"allTerms":["Fall 2025","Fall 2023","Fall 2021","Fall 2019","Fall 2017","Spring 2015","Spring 2013","Spring 2011","Spring 2009","Fall 2007","Spring 2005"]},{"subject":"TAM","number":524,"name":"Micromechanics of Materials","counts":[0,11,0,0],"allTerms":["Spring 2025","Spring 2023","Spring 2021","Spring 2019","Spring 2017","Spring 2015","Spring 2013","Spring 2011","Spring 2009","Spring 2007","Spring 2005"]},{"subject":"TAM","number":529,"name":"Viscoelasticity Theory","counts":[6,4,1,0],"allTerms":["Fall 2024","Spring 2020","Spring 2018","Fall 2017","Summer 2016","Fall 2015","Fall 2013","Fall 2011","Fall 2009","Spring 2008","Spring 2006"]},{"subject":"TAM","number":531,"name":"Inviscid Flow","counts":[22,0,0,0],"allTerms":["Fall 2025","Fall 2024","Fall 2023","Fall 2022","Fall 2021","Fall 2020","Fall 2019","Fall 2018","Fall 2017","Fall 2016","Fall 2015","Fall 2014","Fall 2013","Fall 2012","Fall 2011","Fall 2010","Fall 2009","Fall 2008","Fall 2007","Fall 2006","Fall 2005","Fall 2004"]},{"subject":"TAM","number":532,"name":"Viscous Flow","counts":[0,21,0,0],"allTerms":["Spring 2025","Spring 2024","Spring 2023","Spring 2022","Spring 2021","Spring 2020","Spring 2019","Spring 2018","Spring 2017","Spring 2016","Spring 2015","Spring 2014","Spring 2013","Spring 2012","Spring 2011","Spring 2010","Spring 2009","Spring 2008","Spring 2007","Spring 2006","Spring 2005"]},{"subject":"TAM","number":534,"name":"Non-Newtonian Fluid Mechanics & Rheology","counts":[0,3,0,0],"allTerms":["Spring 2025","Spring 2024","Spring 2023"]},{"subject":"TAM","number":536,"name":"Instability and Transition","counts":[0,9,0,0],"allTerms":["Spring 2024","Spring 2022","Spring 2020","Spring 2018","Spring 2016","Spring 2014","Spring 2012","Spring 2010","Spring 2008"]},{"subject":"TAM","number":537,"name":"Experimental Fluid Mechanics","counts":[7,3,0,0],"allTerms":["Fall 2024","Fall 2022","Fall 2020","Fall 2018","Fall 2016","Fall 2014","Spring 2012","Spring 2010","Spring 2008","Fall 2004"]},{"subject":"TAM","number":538,"name":"Turbulence","counts":[16,0,0,0],"allTerms":["Fall 2023","Fall 2021","Fall 2019","Fall 2017","Fall 2015","Fall 2014","Fall 2013","Fall 2012","Fall 2011","Fall 2010","Fall 2009","Fall 2008","Fall 2007","Fall 2006","Fall 2005","Fall 2004"]},{"subject":"TAM","number":539,"name":"Fluid Mechanics Seminar","counts":[19,19,0,0],"allTerms":["Fall 2025","Spring 2025","Fall 2024","Spring 2024","Fall 2023","Spring 2023","Fall 2022","Spring 2022","Fall 2021","Spring 2021","Fall 2020","Spring 2020","Fall 2019","Spring 2019","Fall 2018","Spring 2018","Fall 2017","Spring 2017","Fall 2016","Spring 2016","Fall 2015","Spring 2015","Fall 2014","Spring 2014","Fall 2013","Spring 2013","Fall 2012","Spring 2012","Fall 2011","Spring 2011","Fall 2010","Spring 2010","Fall 2009","Spring 2009","Fall 2008","Spring 2008","Spring 2005","Fall 2004"]},{"subject":"TAM","number":541,"name":"Mathematical Methods I","counts":[22,0,0,0],"allTerms":["Fall 2025","Fall 2024","Fall 2023","Fall 2022","Fall 2021","Fall 2020","Fall 2019","Fall 2018","Fall 2017","Fall 2016","Fall 2015","Fall 2014","Fall 2013","Fall 2012","Fall 2011","Fall 2010","Fall 2009","Fall 2008","Fall 2007","Fall 2006","Fall 2005","Fall 2004"]},{"subject":"TAM","number":542,"name":"Mathematical Methods II","counts":[0,21,0,0],"allTerms":["Spring 2025","Spring 2024","Spring 2023","Spring 2022","Spring 2021","Spring 2020","Spring 2019","Spring 2018","Spring 2017","Spring 2016","Spring 2015","Spring 2014","Spring 2013","Spring 2012","Spring 2011","Spring 2010","Spring 2009","Spring 2008","Spring 2007","Spring 2006","Spring 2005"]},{"subject":"TAM","number":545,"name":"Advanced Continuum Mechanics","counts":[8,0,0,0],"allTerms":["Fall 2024","Fall 2020","Fall 2018","Fall 2016","Fall 2014","Fall 2011","Fall 2008","Fall 2006"]},{"subject":"TAM","number":549,"name":"Asymptotic Methods","counts":[16,3,0,0],"allTerms":["Fall 2025","Fall 2024","Fall 2023","Fall 2022","Fall 2021","Fall 2020","Fall 2018","Fall 2017","Fall 2016","Fall 2014","Fall 2013","Fall 2012","Fall 2011","Fall 2010","Fall 2009","Fall 2008","Spring 2007","Spring 2006","Spring 2005"]},{"subject":"TAM","number":551,"name":"Solid Mechanics I","counts":[22,0,0,0],"allTerms":["Fall 2025","Fall 2024","Fall 2023","Fall 2022","Fall 2021","Fall 2020","Fall 2019","Fall 2018","Fall 2017","Fall 2016","Fall 2015","Fall 2014","Fall 2013","Fall 2012","Fall 2011","Fall 2010","Fall 2009","Fall 2008","Fall 2007","Fall 2006","Fall 2005","Fall 2004"]},{"subject":"TAM","number":552,"name":"Solid Mechanics II","counts":[0,21,0,0],"allTerms":["Spring 2025","Spring 2024","Spring 2023","Spring 2022","Spring 2021","Spring 2020","Spring 2019","Spring 2018","Spring 2017","Spring 2016","Spring 2015","Spring 2014","Spring 2013","Spring 2012","Spring 2011","Spring 2010","Spring 2009","Spring 2008","Spring 2007","Spring 2006","Spring 2005"]},{"subject":"TAM","number":554,"name":"Plasticity","counts":[11,0,0,0],"allTerms":["Fall 2025","Fall 2023","Fall 2021","Fall 2019","Fall 2017","Fall 2015","Fall 2013","Fall 2011","Fall 2009","Fall 2007","Fall 2005"]},{"subject":"TAM","number":555,"name":"Fracture Mechanics","counts":[8,0,0,0],"allTerms":["Fall 2022","Fall 2020","Fall 2016","Fall 2014","Fall 2010","Fall 2008","Fall 2006","Fall 2004"]},{"subject":"TAM","number":557,"name":"Mechanics of Random Media","counts":[0,5,0,0],"allTerms":["Spring 2024","Spring 2022","Spring 2020","Spring 2018","Spring 2016"]},{"subject":"TAM","number":559,"name":"Atomistic Solid Mechanics","counts":[2,0,0,0],"allTerms":["Fall 2025","Fall 2021"]},{"subject":"TAM","number":561,"name":"Mechanics and Thermodynamics of Soft Matter and Biological Materials","counts":[0,2,0,0],"allTerms":["Spring 2024","Spring 2022"]},{"subject":"TAM","number":570,"name":"Computational Fluid Mechanics","counts":[4,7,0,0],"allTerms":["Fall 2025","Fall 2023","Fall 2021","Fall 2019","Spring 2017","Spring 2015","Spring 2014","Spring 2012","Spring 2010","Spring 2008","Spring 2006"]},{"subject":"TAM","number":574,"name":"Adv Finite Element Methods","counts":[0,10,0,0],"allTerms":["Spring 2025","Spring 2023","Spring 2021","Spring 2019","Spring 2015","Spring 2013","Spring 2011","Spring 2009","Spring 2007","Spring 2005"]},{"subject":"TAM","number":597,"name":"Advanced Independent Study","counts":[22,21,21,0],"allTerms":["Fall 2025","Summer 2025","Spring 2025","Fall 2024","Summer 2024","Spring 2024","Fall 2023","Summer 2023","Spring 2023","Fall 2022","Summer 2022","Spring 2022","Fall 2021","Summer 2021","Spring 2021","Fall 2020","Summer 2020","Spring 2020","Fall 2019","Summer 2019","Spring 2019","Fall 2018","Summer 2018","Spring 2018","Fall 2017","Summer 2017","Spring 2017","Fall 2016","Summer 2016","Spring 2016","Fall 2015","Summer 2015","Spring 2015","Fall 2014","Summer 2014","Spring 2014","Fall 2013","Summer 2013","Spring 2013","Fall 2012","Summer 2012","Spring 2012","Fall 2011","Summer 2011","Spring 2011","Fall 2010","Summer 2010","Spring 2010","Fall 2009","Summer 2009","Spring 2009","Fall 2008","Summer 2008","Spring 2008","Fall 2007","Summer 2007","Spring 2007","Fall 2006","Summer 2006","Spring 2006","Fall 2005","Summer 2005","Spring 2005","Fall 2004"]},{"subject":"TAM","number":598,"name":"Advanced Special Topics","counts":[13,12,0,0],"allTerms":["Spring 2025","Fall 2024","Spring 2024","Fall 2022","Fall 2021","Spring 2021","Fall 2020","Spring 2020","Fall 2019","Fall 2018","Fall 2017","Spring 2017","Fall 2016","Spring 2016","Fall 2015","Spring 2015","Fall 2014","Spring 2014","Fall 2013","Spring 2013","Fall 2012","Spring 2012","Spring 2011","Spring 2010","Fall 2009"]},{"subject":"TAM","number":599,"name":"Thesis Research","counts":[20,21,20,0],"allTerms":["Summer 2025","Spring 2025","Fall 2024","Summer 2024","Spring 2024","Fall 2023","Summer 2023","Spring 2023","Fall 2022","Summer 2022","Spring 2022","Fall 2021","Summer 2021","Spring 2021","Fall 2020","Summer 2020","Spring 2020","Fall 2019","Summer 2019","Spring 2019","Fall 2018","Summer 2018","Spring 2018","Fall 2017","Summer 2017","Spring 2017","Fall 2016","Summer 2016","Spring 2016","Fall 2015","Summer 2015","Spring 2015","Fall 2014","Summer 2014","Spring 2014","Fall 2013","Summer 2013","Spring 2013","Fall 2012","Summer 2012","Spring 2012","Fall 2011","Summer 2011","Spring 2011","Fall 2010","Summer 2010","Spring 2010","Fall 2009","Summer 2009","Spring 2009","Fall 2008","Summer 2008","Spring 2008","Fall 2007","Summer 2007","Spring 2007","Fall 2006","Summer 2006","Spring 2006","Spring 2005","Fall 2004"]}]}